x13_seasonal_adjustment/__init__.py
x13_seasonal_adjustment/arima/__init__.py
x13_seasonal_adjustment/arima/auto_arima.py
x13_seasonal_adjustment/arima/model_selection.py
x13_seasonal_adjustment/core/__init__.py
x13_seasonal_adjustment/core/decomposition.py
x13_seasonal_adjustment/core/result.py
x13_seasonal_adjustment/core/x13.py
x13_seasonal_adjustment/diagnostics/__init__.py
x13_seasonal_adjustment/diagnostics/quality.py
x13_seasonal_adjustment/tests/__init__.py
x13_seasonal_adjustment/tests/seasonality_tests.py
x13_seasonal_adjustment/utils/__init__.py
x13_seasonal_adjustment/utils/preprocessing.py
x13_seasonal_adjustment/utils/validation.py
x13_seasonal_adjustment-0.1.3.dist-info/licenses/LICENSE
x13_seasonal_adjustment-0.1.3.dist-info/METADATA
x13_seasonal_adjustment-0.1.3.dist-info/WHEEL
x13_seasonal_adjustment-0.1.3.dist-info/top_level.txt
x13_seasonal_adjustment-0.1.3.dist-info/RECORD
