Metadata-Version: 2.4
Name: x13-seasonal-adjustment
Version: 0.1.3
Summary: Comprehensive X13-ARIMA-SEATS seasonal adjustment library for Python
Author-email: Gardash Abbasov <gardash.abbasov@gmail.com>
Maintainer-email: Gardash Abbasov <gardash.abbasov@gmail.com>
License: MIT License
Project-URL: Homepage, https://github.com/Gardash023/x13-seasonal-adjustment
Project-URL: Documentation, https://x13-seasonal-adjustment.readthedocs.io
Project-URL: Repository, https://github.com/Gardash023/x13-seasonal-adjustment
Project-URL: Bug Tracker, https://github.com/Gardash023/x13-seasonal-adjustment/issues
Keywords: time-series,seasonal-adjustment,x13,arima,econometrics,statistics
Classifier: Development Status :: 3 - Alpha
Classifier: Intended Audience :: Science/Research
Classifier: Intended Audience :: Financial and Insurance Industry
Classifier: License :: OSI Approved :: MIT License
Classifier: Operating System :: OS Independent
Classifier: Programming Language :: Python :: 3
Classifier: Programming Language :: Python :: 3.8
Classifier: Programming Language :: Python :: 3.9
Classifier: Programming Language :: Python :: 3.10
Classifier: Programming Language :: Python :: 3.11
Classifier: Programming Language :: Python :: 3.12
Classifier: Topic :: Scientific/Engineering :: Mathematics
Classifier: Topic :: Office/Business :: Financial
Requires-Python: >=3.8
License-File: LICENSE
Requires-Dist: numpy>=1.20.0
Requires-Dist: pandas>=1.3.0
Requires-Dist: scipy>=1.7.0
Requires-Dist: statsmodels>=0.13.0
Requires-Dist: matplotlib>=3.3.0
Requires-Dist: scikit-learn>=1.0.0
Provides-Extra: dev
Requires-Dist: pytest>=6.0; extra == "dev"
Requires-Dist: pytest-cov>=2.0; extra == "dev"
Requires-Dist: black>=21.0; extra == "dev"
Requires-Dist: flake8>=3.8; extra == "dev"
Requires-Dist: mypy>=0.900; extra == "dev"
Requires-Dist: sphinx>=4.0; extra == "dev"
Requires-Dist: sphinx-rtd-theme>=1.0; extra == "dev"
Provides-Extra: docs
Requires-Dist: sphinx>=4.0; extra == "docs"
Requires-Dist: sphinx-rtd-theme>=1.0; extra == "docs"
Requires-Dist: nbsphinx>=0.8; extra == "docs"
Requires-Dist: jupyter>=1.0; extra == "docs"
Dynamic: license-file
